<?xml version="1.0" encoding="UTF-8"?>
<followings>

    <following>
        <account_id>1</account_id>
        <follower_id>2</follower_id>
    </following>

    <following>
        <account_id>1</account_id>
        <follower_id>3</follower_id>
    </following>

    <following>
        <account_id>1</account_id>
        <follower_id>4</follower_id>
    </following>

    <following>
        <account_id>2</account_id>
        <follower_id>3</follower_id>
    </following>

    <following>
        <account_id>2</account_id>
        <follower_id>4</follower_id>
    </following>






</followings>